pyazul/__init__.py
pyazul/index.py
pyazul/api/__init__.py
pyazul/api/client.py
pyazul/api/constants.py
pyazul/core/__init__.py
pyazul/core/base.py
pyazul/core/config.py
pyazul/core/exceptions.py
pyazul/models/__init__.py
pyazul/models/schemas.py
pyazul/models/datavault/__init__.py
pyazul/models/datavault/models.py
pyazul/models/payment/__init__.py
pyazul/models/payment/models.py
pyazul/models/payment_page/__init__.py
pyazul/models/payment_page/models.py
pyazul/models/three_ds/__init__.py
pyazul/models/three_ds/models.py
pyazul/models/verification/__init__.py
pyazul/models/verification/models.py
pyazul/services/__init__.py
pyazul/services/datavault.py
pyazul/services/payment_page.py
pyazul/services/secure.py
pyazul/services/transaction.py
pyazul-3.1.0.dist-info/licenses/LICENSE
pyazul-3.1.0.dist-info/METADATA
pyazul-3.1.0.dist-info/WHEEL
pyazul-3.1.0.dist-info/top_level.txt
pyazul-3.1.0.dist-info/RECORD
