Metadata-Version: 2.4
Name: pyazul
Version: 3.1.0
Summary: An Azul Webservices light wrapper for Python.
Author-email: "INDEXA Inc." <info@indexa.do>
License: MIT License
Project-URL: Homepage, https://github.com/indexa-git/pyazul/
Classifier: Programming Language :: Python :: 3
Classifier: License :: OSI Approved :: MIT License
Classifier: Operating System :: OS Independent
Requires-Python: >=3.12
License-File: LICENSE
Requires-Dist: httpx[http2]>=0.28.1
Requires-Dist: pydantic>=2.11.5
Requires-Dist: pydantic-settings>=2.9.1
Requires-Dist: python-dotenv>=1.1.0
Provides-Extra: dev
Requires-Dist: pytest>=8.3.5; extra == "dev"
Requires-Dist: pytest-dotenv>=0.5.2; extra == "dev"
Requires-Dist: pytest-cov>=6.1.1; extra == "dev"
Requires-Dist: pytest-asyncio>=1.0.0; extra == "dev"
Requires-Dist: python-multipart>=0.0.9; extra == "dev"
Requires-Dist: jinja2>=3.1.6; extra == "dev"
Requires-Dist: fastapi>=0.115.12; extra == "dev"
Requires-Dist: flake8>=7.2.0; extra == "dev"
Requires-Dist: flake8-docstrings>=1.7.0; extra == "dev"
Requires-Dist: pydocstyle[toml]>=6.3.0; extra == "dev"
Requires-Dist: interrogate>=1.7.0; extra == "dev"
Requires-Dist: black>=25.1.0; extra == "dev"
Requires-Dist: isort>=6.0.1; extra == "dev"
Requires-Dist: uvicorn>=0.34.2; extra == "dev"
Dynamic: license-file
